aa_validator/__init__.py
aa_validator/py.typed
aws_access_analyzer_validator-0.5.0.dist-info/WHEEL
aws_access_analyzer_validator-0.5.0.dist-info/entry_points.txt
aws_access_analyzer_validator-0.5.0.dist-info/METADATA
aws_access_analyzer_validator-0.5.0.dist-info/RECORD
