Metadata-Version: 2.4
Name: aws-access-analyzer-validator
Version: 0.5.0
Summary: A tool to validate existing identity and resource policies across regions and supported AWS services with AWS IAM Access Analyzer.
Author: Sami Jaktholm
Author-email: Sami Jaktholm <sjakthol@outlook.com>
License-Expression: MIT
Requires-Dist: boto3
Requires-Dist: pydash
Requires-Python: >=3.10
